unijson/__init__.py
unijson/unijson.py
unijson-1.0.0.dist-info/METADATA
unijson-1.0.0.dist-info/RECORD
unijson-1.0.0.dist-info/WHEEL
unijson-1.0.0.dist-info/top_level.txt
