Metadata-Version: 2.1
Name: unijson
Version: 1.0.0
Summary: Universal JSON encoder/decoder for Python objects
Home-page: https://github.com/bpietropaoli/unijson
Author: Bastien Pietropaoli
Author-email: bastien.pietropaoli@gmail.com
License: Apache v2.0
Platform: UNKNOWN
Classifier: Development Status :: 5 - Production/Stable
Classifier: Intended Audience :: Developers
Classifier: License :: OSI Approved :: Apache Software License
Classifier: Operating System :: OS Independent
Classifier: Programming Language :: Python :: 2.7
Classifier: Programming Language :: Python :: 3.4
Classifier: Programming Language :: Python :: 3.5
Classifier: Programming Language :: Python :: 3.6
Classifier: Programming Language :: Python :: 3.7
Classifier: Topic :: Utilities
Requires-Dist: pytz
Requires-Dist: parse
